Metadata-Version: 1.2
Name: scrapy-httpcache
Version: 0.0.5
Summary: A middleware to cache http response for Scrapy
Home-page: https://github.com/xiaowangwindow/scrapy-httpcache
Author: Alex Wang
Maintainer: Alex Wang
Maintainer-email: xiaowangwindow@163.com
License: BSD
Platform: UNKNOWN
Classifier: Framework :: Scrapy
Classifier: Development Status :: 2 - Pre-Alpha
Classifier: Environment :: Plugins
Classifier: Intended Audience :: Developers
Classifier: License :: OSI Approved :: BSD License
Classifier: Operating System :: OS Independent
Classifier: Programming Language :: Python
Classifier: Programming Language :: Python :: 2
Classifier: Programming Language :: Python :: 2.7
Classifier: Programming Language :: Python :: 3
Classifier: Programming Language :: Python :: 3.4
Classifier: Programming Language :: Python :: 3.5
Classifier: Programming Language :: Python :: 3.6
Classifier: Topic :: Internet :: WWW/HTTP
Classifier: Topic :: Software Development :: Libraries :: Python Modules
